tests/__init__.py
tests/test_timeFormater.py
time_operators/__init__.py
time_operators/operators.py
time_operators-0.1.0.dist-info/LICENSE
time_operators-0.1.0.dist-info/METADATA
time_operators-0.1.0.dist-info/WHEEL
time_operators-0.1.0.dist-info/top_level.txt
time_operators-0.1.0.dist-info/RECORD
